Metadata-Version: 2.1
Name: fastapi-chat-sdk
Version: 0.0.4
Summary: FastAPI microservice for chatting
Home-page: https://github.com/wykyee/fastapi_chat
Author: Danylo Vasyliuk
Author-email: danil.vasiliuk@gmail.com
License: BSD-3-Clause  # Example license
Platform: UNKNOWN
Classifier: Environment :: Web Environment
Classifier: Intended Audience :: Developers
Classifier: License :: OSI Approved :: MIT License
Classifier: Operating System :: OS Independent
Classifier: Programming Language :: Python
Classifier: Programming Language :: Python :: 3
Classifier: Programming Language :: Python :: 3 :: Only
Classifier: Topic :: Internet :: WWW/HTTP
Classifier: Topic :: Internet :: WWW/HTTP :: Dynamic Content
Requires-Python: >=3.8
License-File: LICENSE
Requires-Dist: aioredis (==1.3.1)
Requires-Dist: fastapi (==0.70.0)
Requires-Dist: httpx (==0.13.3)
Requires-Dist: uvicorn (==0.11.5)
Requires-Dist: websockets (==8.1)
